MANIFEST.in
__info__.py
setup.py
./appomatic_ckeditor.egg-info/SOURCES.txt
./appomatic_ckeditor.egg-info/dependency_links.txt
./appomatic_ckeditor.egg-info/requires.txt
./appomatic_ckeditor.egg-info/top_level.txt
appomatic_ckeditor/__app__.py
appomatic_ckeditor/__init__.py
appomatic_ckeditor/__settings__.py
appomatic_ckeditor/__urls__.py
appomatic_ckeditor.egg-info/PKG-INFO
appomatic_ckeditor.egg-info/SOURCES.txt
appomatic_ckeditor.egg-info/dependency_links.txt
appomatic_ckeditor.egg-info/requires.txt
appomatic_ckeditor.egg-info/top_level.txt