Metadata-Version: 1.0
Name: appomatic-ckeditor
Version: 0.0.31
Summary: Django admin CKEditor integration.
Home-page: http://github.com/shaunsephton/django-ckeditor
Author: RedHog (Egil Moeller)
Author-email: egil.moller@freecode.no
License: GPL
Keywords: appomatic ckeditor
Platform: UNKNOWN
